simplexl/__init__.py
simplexl-1.0.2.dist-info/LICENSE
simplexl-1.0.2.dist-info/WHEEL
simplexl-1.0.2.dist-info/METADATA
simplexl-1.0.2.dist-info/RECORD
