Metadata-Version: 2.1
Name: simplexl
Version: 1.0.2
Summary: 
Home-page: https://github.com/devarajug/simplexl
Author: Devaraju Garigapati
Author-email: devarajugarigapati@gmail.com
Requires-Python: >=3.8,<4.0
Classifier: Programming Language :: Python :: 3
Classifier: Programming Language :: Python :: 3.10
Classifier: Programming Language :: Python :: 3.8
Classifier: Programming Language :: Python :: 3.9
Requires-Dist: openpyxl (>=3.0.10,<4.0.0)
Project-URL: Repository, https://github.com/devarajug/simplexl
